ZTData/__init__.py
ZTData/client.py
ZTData/websocket_client.py
ZTData/generated/__init__.py
ZTData/generated/datasource_pb2.py
ZTData/generated/datasource_pb2_grpc.py
ztdata-0.3.15.dist-info/licenses/LICENSE
ztdata-0.3.15.dist-info/METADATA
ztdata-0.3.15.dist-info/WHEEL
ztdata-0.3.15.dist-info/top_level.txt
ztdata-0.3.15.dist-info/RECORD
