Metadata-Version: 2.4
Name: ztdata
Version: 0.3.15
Summary: 统一数据库客户端SDK
Home-page: https://git.ztquant.com/ztData/ztDataClient
Author: ZTQuant团队
Author-email: liubocheng@ztquant.com
License: MIT
Classifier: Programming Language :: Python :: 3
Classifier: License :: OSI Approved :: MIT License
Classifier: Operating System :: OS Independent
Requires-Python: >=3.6
License-File: LICENSE
Requires-Dist: grpcio>=1.44.0
Requires-Dist: protobuf==5.29.0
Requires-Dist: websocket-client
Requires-Dist: pandas>=2.3.1
Requires-Dist: pyarrow>=14.0.1
Dynamic: author
Dynamic: author-email
Dynamic: classifier
Dynamic: description
Dynamic: description-content-type
Dynamic: home-page
Dynamic: license
Dynamic: license-file
Dynamic: requires-dist
Dynamic: requires-python
Dynamic: summary
